wordtm/__init__.py
wordtm/meta.py
wordtm/pivot.py
wordtm/quot.py
wordtm/ta.py
wordtm/tm.py
wordtm/util.py
wordtm/version.py
wordtm/viz.py
wordtm/data/__init__.py
wordtm/dictionary/__init__.py
wordtm/images/__init__.py
wordtm-0.4.6.dist-info/LICENSE.txt
wordtm-0.4.6.dist-info/METADATA
wordtm-0.4.6.dist-info/WHEEL
wordtm-0.4.6.dist-info/top_level.txt
wordtm-0.4.6.dist-info/RECORD
