Metadata-Version: 2.1
Name: wordtm
Version: 0.4.6
Summary: Topic Modeling Package
Author: Dr. Johnny CHENG
Author-email: <drjohnnycheng@gmail.com>
Project-URL: Documentation, https://drjohnnycheng.github.io/wordtm
Keywords: word,scripture,topic modeling,visualization,low-code,pro-code,network analysis,BERTopic,LDA,NFM
Classifier: Development Status :: 3 - Alpha
Classifier: Intended Audience :: Education
Classifier: Intended Audience :: Science/Research
Classifier: Intended Audience :: Religion
Classifier: Programming Language :: Python :: 3
Classifier: Operating System :: Microsoft :: Windows
Classifier: Operating System :: MacOS :: MacOS X
License-File: LICENSE.txt
Requires-Dist: numpy
Requires-Dist: pandas
Requires-Dist: importlib-resources
Requires-Dist: regex
Requires-Dist: nltk
Requires-Dist: matplotlib
Requires-Dist: wordcloud
Requires-Dist: pillow
Requires-Dist: jieba
Requires-Dist: gensim
Requires-Dist: pyLDAvis
Requires-Dist: bertopic
Requires-Dist: transformers
Requires-Dist: spacy
Requires-Dist: seaborn
Requires-Dist: importlib
Requires-Dist: networkx
Requires-Dist: plotly
Requires-Dist: IPython
Requires-Dist: scikit-learn
Requires-Dist: torch
